setup.py
SHICTHRSWMICManager/__init__.py
SHICTHRSWMICManager.egg-info/PKG-INFO
SHICTHRSWMICManager.egg-info/SOURCES.txt
SHICTHRSWMICManager.egg-info/dependency_links.txt
SHICTHRSWMICManager.egg-info/not-zip-safe
SHICTHRSWMICManager.egg-info/requires.txt
SHICTHRSWMICManager.egg-info/top_level.txt
SHICTHRSWMICManager/utils/SHRWMICManager_check_is_wmic_available.py
SHICTHRSWMICManager/utils/SHRWMICManager_install_wmic_win10.py
SHICTHRSWMICManager/utils/SHRWMICManager_install_wmic_win11.py
SHICTHRSWMICManager/utils/SHRWMICManager_uninstall_wmic_win11.py
SHICTHRSWMICManager/utils/__init__.py