Metadata-Version: 2.4
Name: SHICTHRSWMICManager
Version: 1.3.0
Summary: SHICTHRS WMIC Manager
Home-page: https://github.com/JNTMTMTM/SHICTHRS_WMICManager
Author: SHICTHRS
Author-email: contact@shicthrs.com
License: GPL-3.0
Requires-Dist: colorama==0.4.6
Dynamic: author
Dynamic: author-email
Dynamic: home-page
Dynamic: license
Dynamic: requires-dist
Dynamic: summary
